{
  "name": "Switchboard Charcoal",
  "type": "dark",
  "colors": {
    "editor.background": "#0f0f0f",
    "editor.foreground": "#e2e8f0",
    "sideBar.background": "#111111",
    "sideBar.foreground": "#8b949e",
    "activityBar.background": "#0a0a0a",
    "activityBar.foreground": "#e2e8f0",
    "statusBar.background": "#0a0a0a",
    "statusBar.foreground": "#8b949e",
    "titleBar.activeBackground": "#0a0a0a",
    "titleBar.activeForeground": "#8b949e",
    "panel.background": "#111111",
    "tab.activeBackground": "#0f0f0f",
    "tab.inactiveBackground": "#0a0a0a",
    "tab.activeForeground": "#e2e8f0",
    "tab.inactiveForeground": "#8b949e",
    "editorGroupHeader.tabsBackground": "#0a0a0a",
    "focusBorder": "#58a6ff66",
    "list.activeSelectionBackground": "#58a6ff1a",
    "list.hoverBackground": "#ffffff0d",
    "input.background": "#1a1a1a",
    "dropdown.background": "#1a1a1a",
    "button.background": "#58a6ff",
    "badge.background": "#58a6ff",
    "editorLineNumber.foreground": "#484f58",
    "editorCursor.foreground": "#58a6ff",
    "scrollbarSlider.background": "#ffffff14",
    "editorWidget.background": "#1c1c1c",
    "quickInput.background": "#1c1c1c",
    "notifications.background": "#1c1c1c",
    "terminal.background": "#0a0a0a",
    "widget.border": "#ffffff12",
    "panel.border": "#ffffff12",
    "sideBar.border": "#ffffff12",
    "editorGroup.border": "#ffffff12"
  },
  "tokenColors": []
}